{
  "dataList": [
    {
      "id": 0,
      "place": "Дагуаньюань - Особый лекционный зал",
      "model": "가시춘",
      "title": "Глава Хунъюаня",
      "content": "Понятно... когда ты говоришь, что просто избегал всего, что казалось неправильным, полагаясь на «предчувствие», ты на самом деле рефлекторно определял угрозу, считывая обстановку и связывая её со своим интуитивным опытом."
    },
    {
      "id": 1,
      "model": "싱클레어",
      "content": "Ага, так ты использовал тревожное дыхание госпожи Дайюй как подсказку..."
    },
    {
      "id": 2,
      "model": "가시춘",
      "title": "Глава Хунъюаня",
      "content": "...Так вот как тебе удавалось выживать так долго."
    },
    {
      "id": 3,
      "model": "홍루",
      "content": "Послушай внимательно, Сичунь. Я знаю, что адепты Хэйшоу придут к тебе на помощь по одному мановению твоей руки,"
    },
    {
      "id": 4,
      "model": "홍루",
      "content": "и знаю, что твою резиденцию, Нуаньсяну, лучшие мастера превратят в неприступную крепость, доверху наполненную всевозможными спасительными Болюсами."
    },
    {
      "id": 5,
      "model": "홍루",
      "content": "И всё же, однажды настанет день, когда ты почувствуешь это подкрадывающееся ощущение, источник которого не сможешь определить. И когда это случится, я надеюсь, ты не отмахнёшься от него, посчитав его пустяком."
    },
    {
      "id": 6,
      "model": "가시춘",
      "title": "Глава Хунъюаня",
      "content": "Пф, беспокоишься о пустяках."
    },
    {
      "id": 7,
      "content": "Цзя Сичунь резко отвернулась от Хон Лу, словно желая выказать своё недовольство, но..."
    },
    {
      "id": 8,
      "content": "...её смягчившееся выражение лица говорило о том, что она была рада его заботе."
    }
  ]
}