{
  "dataList": [
    {
      "id": 0,
      "place": "В Мефистофеле",
      "content": "Вскоре после разрешения происшествия с Синклером…"
    },
    {
      "id": 1,
      "model": "그레고르",
      "content": "Кстати, когда вы говорили про корпорацию K, то не перепутали ли место назначения с подворотнями одиннадцатого Района?"
    },
    {
      "id": 2,
      "model": "그레고르",
      "content": "Я не успел спросить раньше, поскольку все были навеселе…"
    },
    {
      "id": 3,
      "model": "베르길리우스",
      "content": "Я не допускаю подобных оговорок."
    },
    {
      "id": 4,
      "model": "베르길리우스",
      "content": "Тебе не послышалось, Грегор. Мы едем в Гнездо корпорации K."
    },
    {
      "id": 5,
      "model": "그레고르",
      "content": "Но ведь чтобы попасть в Гнездо…"
    },
    {
      "id": 6,
      "model": "베르길리우스",
      "content": "Да, надо пройти досмотр."
    },
    {
      "id": 7,
      "model": "로쟈",
      "content": "У меня нет визы корпорации K. Только не говорите, что она есть у всех остальных?"
    },
    {
      "id": 8,
      "model": "히스클리프",
      "content": "Чё ты на меня пялишь?"
    },
    {
      "id": 9,
      "model": "료슈",
      "content": "Решение простое: СОВ."
    },
    {
      "id": 10,
      "model": "료슈",
      "content": "А затем ОК, пока дорога не расчистится."
    },
    {
      "id": 11,
      "model": "료슈",
      "content": "Вкратце, СОВОК. Хехе…"
    },
    {
      "id": 12,
      "content": "Всё меньше грешников задавались вопросом, что же значат аббревиатуры Рёшу."
    },
    {
      "id": 13,
      "model": "이스마엘",
      "content": "Компании по типу «Лимбус» должны предоставлять бесплатный пропуск."
    },
    {
      "id": 14,
      "model": "이스마엘",
      "content": "К тому же метод, предложенный мисс Рёшу, займёт уйму времени. Это насколько надо недооценивать Гнездо, охраняемое Крылом, чтобы предложить подобное?"
    },
    {
      "id": 15,
      "model": "단테",
      "content": "<И видимо никто не берёт в расчёт, насколько я пострадаю от этого СОВОКа?>"
    },
    {
      "id": 16,
      "content": "К сожалению, ни один из грешников мне не ответил."
    },
    {
      "id": 17,
      "model": "베르길리우스",
      "content": "Как Измаил и сказала, мы пройдём без визы."
    },
    {
      "id": 18,
      "model": "베르길리우스",
      "content": "За компанией «Лимбус» стоит множество акционеров из самых разных сфер."
    },
    {
      "id": 19,
      "model": "홍루",
      "content": "Ах, тогда вам должен быть знаком акционер из корпорации H?"
    },
    {
      "id": 20,
      "model": "홍루",
      "content": "Он лично заехал к нам домой, когда мой младший брат, ещё будучи ребёнком, настоял на том, что хочет заиметь красный паспорт."
    },
    {
      "id": 21,
      "model": "베르길리우스",
      "content": "Вряд ли, простой гид вроде меня не в той позиции, дабы знать о подобных вещах."
    },
    {
      "id": 22,
      "model": "베르길리우스",
      "content": "Это не тот вопрос, который стоит времени."
    },
    {
      "id": 23,
      "model": "홍루",
      "content": "Жёстко…"
    },
    {
      "id": 24,
      "model": "베르길리우스",
      "content": "Сейчас куда важнее добраться до контрольно-пропускного пункта."
    },
    {
      "id": 25,
      "model": "베르길리우스",
      "content": "Строгий досмотр означает, что будет полно людей, пытающихся найти способ пройти \"попроще\", в том числе и грубой силой."
    },
    {
      "id": 26,
      "model": "뫼르소",
      "content": "…Около автобуса слышны нарушители."
    },
    {
      "id": 27,
      "model": "단테",
      "content": "<Ну… Как обычно.>"
    }
  ]
}