{
  "dataList": [
    {
      "id": 0,
      "place": "Грузовик LCCB",
      "model": "9장소드다침",
      "content": "Го-готовьтесь к бою, немедленно..."
    },
    {
      "id": 1,
      "model": "9장소드다침",
      "content": "Я... больше не в состоянии действовать, как вы сами видите... Мне нужна... ваша помощь."
    },
    {
      "id": 2,
      "content": "Сод рухнула на пол прежде, чем мы успели спросить, в порядке ли она или что случилось с её рукой."
    },
    {
      "id": 3,
      "model": "9장소드다침",
      "content": "Сразу после встречи с господином Вергилием... я... попала в засаду..."
    },
    {
      "id": 4,
      "model": "9장소드다침",
      "content": "И нападавшие... нападавшие будут здесь с минуты на минуту."
    },
    {
      "id": 5,
      "content": "Там, где прежде её решимость не колебалась даже перед лицом смерти..."
    },
    {
      "id": 6,
      "content": "...теперь в её глазах застыло тяжкое отчаяние."
    },
    {
      "id": 7,
      "model": "오티스",
      "content": "Сколько противников?"
    },
    {
      "id": 8,
      "model": "9장소드다침",
      "content": "...Двое."
    },
    {
      "id": 9,
      "model": "9장소드다침",
      "content": "Пока господин Вергилий разбирался с одним из них, я..."
    },
    {
      "id": 10,
      "model": "로쟈",
      "content": "Верг?"
    },
    {
      "id": 11,
      "content": "Лицо Роди вновь обрело краски, стоило ей услышать имя Вергилия."
    },
    {
      "id": 12,
      "model": "로쟈",
      "content": "Ну... Может тогда Верг уже на обратном пути, после того как вытер пол ими обоими?"
    },
    {
      "id": 13,
      "model": "9장소드다침",
      "content": "Н... нет. Не думаю..."
    },
    {
      "id": 14,
      "model": "9장소드다침",
      "content": "Это Харон..."
    },
    {
      "id": 15,
      "model": "9장소드다침",
      "content": "Я... я потеряла её."
    },
    {
      "id": 16,
      "model": "9장소드다침",
      "content": "Они оторвали руку, которой я держала Харон..."
    },
    {
      "id": 17,
      "model": "9장소드다침",
      "content": "Я не должна была отпускать, я не должна была позволить этому случиться..."
    },
    {
      "id": 18,
      "model": "돈키호테",
      "content": "Неужто ты не смогла удержать юную Харон? Как, что?.."
    },
    {
      "id": 19,
      "content": "Сод поморщилась, её лицо выражало смесь вины и замешательства."
    },
    {
      "id": 20,
      "content": "Это было далеко от её обычного, собранного образа."
    },
    {
      "id": 21,
      "model": "홍루",
      "content": "...Они взяли Харон в заложники?"
    },
    {
      "id": 22,
      "model": "9장소드다침",
      "content": "Да. Я... не смогла помешать им забрать... Харон."
    },
    {
      "id": 23,
      "model": "싱클레어",
      "content": "А что насчёт Пилота?.."
    },
    {
      "id": 24,
      "model": "9장소드다침",
      "content": "......."
    },
    {
      "id": 25,
      "model": "9장소드다침",
      "content": "Пилот был тяжело ранен, но... когда я видела его в последний раз, он был в сознании."
    },
    {
      "id": 26,
      "model": "이스마엘",
      "content": "...Нам нужно готовиться к бою. Сейчас же."
    },
    {
      "id": 27,
      "model": "오티스",
      "content": "По крайней мере, наша текущая цель ясна, Исполнительный Менеджер. Сначала устранить преследователей, затем спасти Харон. Хотя точные мотивы преступников ещё не раскрыты..."
    },
    {
      "id": 28,
      "model": "9장소드다침",
      "content": "Возможно, нам придётся столкнуться с несколькими фронтами. По пути сюда я поймала короткую передачу из штаб-квартиры, и..."
    },
    {
      "id": 29,
      "content": "*тзззззт*"
    },
    {
      "id": 30,
      "content": "В тишине грузовика внезапно раздаётся треск белого шума."
    },
    {
      "id": 31,
      "model": "9장소드다침",
      "content": "...!"
    },
    {
      "id": 32,
      "model": "9장소드다침",
      "content": "Ах..."
    },
    {
      "id": 34,
      "model": "LCE연구원1",
      "teller": "Передатчик",
      "content": "Любая станция, ответьте... ответьте..."
    },
    {
      "id": 35,
      "content": "Сод замерла, уставившись на динамик радио."
    },
    {
      "id": 36,
      "content": "Грегор первым начал действовать вместо неё."
    },
    {
      "id": 37,
      "model": "그레고르",
      "content": "Это LCB, я вас слышу. Какова ваша обстановка? Приём."
    },
    {
      "id": 38,
      "model": "LCE연구원1",
      "teller": "Передатчик",
      "content": "Исследовательский центр штаб-квартиры—"
    },
    {
      "id": 39,
      "model": "그레고르",
      "content": "Исследовательский центр?"
    },
    {
      "id": 40,
      "model": "LCE연구원1",
      "teller": "Передатчик",
      "content": "По-по-под-атакой—"
    },
    {
      "id": 41,
      "model": "검지아비상",
      "teller": "Передатчик",
      "title": "???",
      "content": "Моя дорогая дочь. Надеюсь, у тебя там всё было хорошо."
    },
    {
      "id": 42,
      "place": "Грузовик LCCB",
      "model": "검지아비상",
      "teller": "Передатчик",
      "title": "???",
      "content": "Но не думаешь ли ты, что тебе пора перестать играть и вернуться домой?"
    },
    {
      "id": 43,
      "content": "Воцаряется абсолютная тишина, когда ласковый зов обрывает леденящий душу крик на другом конце."
    },
    {
      "id": 44,
      "content": "Голос, донёсшийся из радио, был не иначе как нежным."
    },
    {
      "id": 45,
      "content": "И... было несложно догадаться, кто был этой «дочерью»."
    },
    {
      "id": 46,
      "model": "료슈2",
      "content": "...Ха."
    },
    {
      "id": 47,
      "model": "료슈",
      "content": "Пауки сплели свою паутину, Часы."
    },
    {
      "id": 48,
      "model": "단테",
      "content": "<Паутину?>"
    },
    {
      "id": 49,
      "model": "료슈",
      "content": "И она сплетена так искусно, что её не обойти."
    },
    {
      "id": 50,
      "content": "В этот момент я вспомнил кое-что из слов Лэй Хэна — «Дом Пауков»."
    },
    {
      "id": 51,
      "content": "Вспоминая, как бурно тогда отреагировала Рёшу..."
    },
    {
      "id": 52,
      "model": "단테",
      "content": "<Думаешь... думаешь, эти нападавшие как-то связаны с тем, ну... парнем Лэй Хэном, которого мы встретили раньше?>"
    },
    {
      "id": 53,
      "model": "료슈2",
      "content": "Вряд ли."
    },
    {
      "id": 54,
      "model": "료슈",
      "content": "Он был лишь одним из моих многочисленных мимолётных наставников."
    },
    {
      "id": 55,
      "model": "싱클레어",
      "content": "Т-тогда кто мог — это же штаб-квартира, чёрт возьми!.."
    },
    {
      "id": 56,
      "model": "9장소드다침",
      "content": "Я не знаю. Штаб-квартира, это... это не то место, куда кто-то может просто ворваться силой..."
    },
    {
      "id": 57,
      "model": "9장소드다침",
      "content": "Проникнуть в такое место?.. Это совершенно немыслимо..."
    },
    {
      "id": 58,
      "model": "단테",
      "content": "<.......>"
    },
    {
      "id": 59,
      "content": "Что теперь?"
    },
    {
      "id": 60,
      "content": "Обычно я использовал свою интуицию, чтобы выбрать лучший план действий и вести Грешников во время миссии."
    },
    {
      "id": 61,
      "content": "Но кто бы мог подумать, что штаб-квартира, которая должна была проинструктировать нас об этой самой миссии, подвергнется нападению... особенно пока мы остались без проводника?"
    },
    {
      "id": 62,
      "model": "료슈",
      "content": "*пффф*"
    },
    {
      "id": 63,
      "model": "료슈",
      "content": "Ладно. Я не ожидала, что они сами придут искать меня."
    },
    {
      "id": 64,
      "model": "료슈",
      "content": "В конце концов, когда Пауки сплели свою паутину, они склонны ждать, пока добыча сама в неё угодит."
    },
    {
      "id": 65,
      "content": "Струйка сигаретного дыма на мгновение задержалась, прежде чем раствориться в воздухе. Когда я посмотрел на лицо Рёшу, то увидел..."
    },
    {
      "id": 66,
      "content": "...выражение странной эйфории."
    },
    {
      "id": 67,
      "model": "9장소드다침",
      "content": "......."
    },
    {
      "id": 68,
      "model": "9장소드다침",
      "content": "Рёшу, неужели всё это для тебя лишь..."
    },
    {
      "id": 69,
      "model": "9장소드다침",
      "content": "...какое-то забавное развлечение?"
    },
    {
      "id": 70,
      "content": "Сод бросила недоверчивый взгляд на Рёшу, которая невозмутимо докуривала остаток сигареты до пепла."
    },
    {
      "id": 71,
      "model": "료슈",
      "content": "Именно так."
    },
    {
      "id": 72,
      "model": "료슈",
      "content": "Долгожданный миг наконец нашёл меня."
    },
    {
      "id": 73,
      "model": "료슈",
      "content": "С чего бы мне не радоваться?"
    },
    {
      "id": 74,
      "model": "9장소드다침",
      "content": "Это же просто —"
    },
    {
      "id": 75,
      "model": "료슈",
      "content": "Но... не смей предполагать лишнего."
    },
    {
      "id": 76,
      "model": "료슈",
      "content": "Моё предвкушение грядущего удовольствия... не помешает моей эффективности."
    },
    {
      "id": 77,
      "model": "료슈",
      "content": "Я ни разу... не позволяла наслаждению мешать серьёзному отношению к работе."
    },
    {
      "id": 78,
      "model": "료슈",
      "content": "Никогда раньше, и не сейчас."
    },
    {
      "id": 79,
      "model": "단테",
      "content": "<……>"
    },
    {
      "id": 80,
      "model": "료슈",
      "content": "Ты сказала, нападавшие скоро будут здесь. Тот, кто забрал водителя, тоже придёт?"
    },
    {
      "id": 81,
      "model": "9장소드다침",
      "content": "... Харон —"
    },
    {
      "id": 82,
      "model": "9장소드다침",
      "content": "Если с мисс Харон что-нибудь случится, я..."
    },
    {
      "id": 83,
      "model": "9장소드다침",
      "content": "...я не смогу заставить себя предстать перед Красным Взором."
    },
    {
      "id": 84,
      "model": "료슈",
      "content": "Цск. Это ни к чему не ведёт."
    },
    {
      "id": 85,
      "model": "료슈",
      "content": "Пауки не тронут водителя."
    },
    {
      "id": 86,
      "model": "료슈",
      "content": "Она лишь наживка, чтобы выманить добычу покрупнее."
    },
    {
      "id": 87,
      "model": "료슈",
      "content": "Так что прекрати паниковать и приготовь всё для нас. Это выглядит неприглядно."
    },
    {
      "id": 88,
      "model": "9장소드다침",
      "content": "...Что?"
    },
    {
      "id": 89,
      "model": "료슈2",
      "content": "Чёрный Ход в этом грузовике. Может ли он соединить нас напрямую с исследовательским центром штаб-квартиры прямо сейчас?"
    },
    {
      "id": 90,
      "model": "9장소드다침",
      "content": "П-погоди. Может, но..."
    },
    {
      "id": 91,
      "model": "9장소드다침",
      "content": "Чтобы использовать портал Черного Хода, ведущий прямиком в штаб-квартиру, мне нужно подтвердить код безопасности, написанный специально для каждой координаты. Это... займёт некоторое время."
    },
    {
      "id": 92,
      "model": "료슈",
      "content": "Хех. Как раз хватит, чтобы разобраться с твоим преследователем."
    },
    {
      "id": 93,
      "content": "Пока Сод управлялась с механизмами машины своей оставшейся рукой..."
    },
    {
      "id": 94,
      "content": "...Грешники начали следить за окружением, держа оружие наготове."
    },
    {
      "id": 95,
      "model": "이스마엘",
      "content": "Так мы уверены, что направляться в штаб-квартиру — хорошая идея? Мне кажется, мы сами идём в ловушку..."
    },
    {
      "id": 96,
      "model": "싱클레어",
      "content": "...А что, если нам попросить помощи у Дагуаньюаня?"
    },
    {
      "id": 97,
      "model": "오티스",
      "content": "Это <i>могло бы</i> стать решением, да. Однако, поскольку это касается нашей штаб-квартиры, разрешение этого кризиса с помощью Крыла, даже того, с чьим лидером мы в хороших отношениях... потребует возврата огромного долга."
    },
    {
      "id": 98,
      "model": "오티스",
      "content": "Ваше решение, Исполнительный Менеджер?"
    },
    {
      "id": 99,
      "model": "단테",
      "content": "<……>"
    },
    {
      "id": 100,
      "model": "단테",
      "content": "<...Мы отправимся прямиком в исследовательский центр штаб-квартиры, как только Сод откроет портал.>"
    },
    {
      "id": 101,
      "content": "Было несложно интуитивно понять, что настал черёд Рёшу, учитывая её явное воодушевление."
    },
    {
      "id": 102,
      "content": "Если так... то Чёрный Ход, ведущий в штаб-квартиру, которым намерена воспользоваться Рёшу, должен быть тем путём, по которому нам суждено пройти в этот раз."
    },
    {
      "id": 103,
      "model": "료슈2",
      "content": "Получше приготовьтесь."
    },
    {
      "id": 104,
      "model": "료슈",
      "content": "То, что ждёт нас впереди, без тени сомнения — ад..."
    },
    {
      "id": 105,
      "model": "료슈",
      "content": "...и там, в его глубинах... лежит нечто, что всегда поджидало меня."
    },
    {
      "id": 106,
      "model": "이상",
      "content": "......."
    },
    {
      "id": 107,
      "model": "이상",
      "content": "Что-то скрипит над нами, ступая по крыше транспорта... нас обнаружили."
    },
    {
      "id": 108,
      "model": "히스클리프",
      "content": "Эй, тогда не стоит ли нам убраться из грузовика, пока он не обвалился нам на головы?"
    },
    {
      "id": 109,
      "model": "이스마엘",
      "content": "Нет. Сингулярность Корпорации P защищает этот грузовик, помнишь? Нечто, что должно держать в безопасности всё, что внутри. Нам стоит просто затаиться здесь, пока—"
    },
    {
      "id": 110,
      "model": "로쟈",
      "content": "Т-ты в этом уверена? Я вижу ма-а-асенькую трещину в потолке!"
    },
    {
      "id": 111,
      "model": "이스마엘",
      "content": "Трещина? Это... не имеет смысла. Потолок должен быть достаточно эластичным, чтобы гнуться под большинством физических воздействий, а не трескаться."
    },
    {
      "id": 112,
      "model": "파우스트",
      "content": "...Это правда, что внешняя оболочка этого средства передвижения использует Сингулярность Корпорации P."
    },
    {
      "id": 113,
      "model": "파우스트",
      "content": "Именно поэтому этот грузовик внутри просторнее, чем кажется снаружи, и обладает хорошей защитой от внешних сил."
    },
    {
      "id": 114,
      "model": "파우스트",
      "content": "Однако, в отличие от экспериментальной модели, на которую мы садились в Корпорации P, это транспортное средство, похоже, является более... бюджетной моделью, используемой как шаттл для развёртывания Команды \"До\"."
    },
    {
      "id": 115,
      "model": "단테",
      "content": "<...?>"
    },
    {
      "id": 116,
      "model": "파우스트",
      "content": "Это значит, что для работы технологий Сингулярности на должном уровне требуются более высокие инвестиции. Бюджетные модели — даже те, что используют Сингулярности — всё равно могут быть пробиты."
    },
    {
      "id": 117,
      "model": "히스클리프",
      "content": "Значит, они сэкономили."
    },
    {
      "id": 118,
      "model": "료슈",
      "content": "Тогда нападавший — не один из Отцов-воспитателей из Дома Пауков."
    },
    {
      "id": 119,
      "model": "료슈",
      "content": "Будь это один из них... первый же удар разнёс бы эту стену в щепки."
    },
    {
      "id": 120,
      "model": "료슈",
      "content": "Полагаю, начинать сразу с верхушки было бы довольно пресным развитием сюжета."
    },
    {
      "id": 121,
      "model": "싱클레어",
      "content": "Отцы-<i>воспитатели</i>?.. Погоди, ты о тех же людях, которых Лэй Хэн—"
    },
    {
      "id": 122,
      "model": "오티스",
      "content": "...У нас будет время для предположений позже."
    },
    {
      "id": 123,
      "model": "오티스",
      "content": "Исполнительный Менеджер, потолок сейчас обвалится!"
    },
    {
      "id": 124,
      "model": "단테",
      "content": "<...Бейте на поражение, как только они окажутся внутри.>"
    },
    {
      "id": 125,
      "model": "단테"
    },
    {
      "id": 126,
      "model": "엄지제자",
      "teller": "???",
      "title": "???",
      "content": "......."
    },
    {
      "id": 127,
      "model": "오티스",
      "content": "К бою, люди!"
    },
    {
      "id": 128,
      "model": "단테",
      "content": "<...! Стойте, не нападайте!>"
    },
    {
      "id": 129,
      "content": "Хотя мы уже приготовились проткнуть незваного гостя, как только он шагнёт внутрь..."
    },
    {
      "id": 130,
      "content": "...нам пришлось немедленно отказаться от этой идеи, когда мы увидели, кого он несёт."
    },
    {
      "id": 131,
      "model": "9장소드다침",
      "content": "...Харон!.."
    },
    {
      "id": 132,
      "model": "엄지제자",
      "teller": "???",
      "title": "???",
      "content": "Она лишь без сознания — и всё ещё дышит."
    },
    {
      "id": 133,
      "model": "오티스",
      "content": "Понимаю. Ты отрубил руку Сод, чтобы у тебя было что-то, по чему её можно выследить."
    },
    {
      "id": 134,
      "model": "엄지제자",
      "teller": "???",
      "title": "???",
      "content": "И она прямиком отправилась искать помощи у своих товарищей..."
    },
    {
      "id": 135,
      "model": "엄지제자",
      "teller": "???",
      "title": "???",
      "content": "С нашей стороны это было действительно верным решением — подождать и посмотреть, как она отреагирует."
    },
    {
      "id": 136,
      "content": "Незваный гость продолжил, взглянув в сторону Сод."
    },
    {
      "id": 137,
      "content": "Словно в ответ на это, Рёшу положила руку..."
    },
    {
      "id": 138,
      "content": "...на ножны."
    },
    {
      "id": 139,
      "model": "단테",
      "content": "<...Рёшу?>"
    },
    {
      "id": 140,
      "model": "료슈",
      "content": "*пффф* С.В.Н.Н.С. Они не посмеют навредить водителю автобуса."
    },
    {
      "id": 141,
      "model": "료슈",
      "content": "Так что не поднимай шума, Часы."
    },
    {
      "id": 142,
      "model": "싱클레어",
      "content": "А?! Что значит «ничего не случится» — Рёшу?!"
    },
    {
      "id": 143,
      "content": "Рёшу проигнорировала Синклера и бросилась к незваному гостю, её ножны рассекли воздух."
    },
    {
      "id": 144,
      "model": "료슈",
      "content": "Охо... парировал, значит?"
    },
    {
      "id": 145,
      "model": "엄지제자",
      "teller": "???",
      "title": "???",
      "content": "...Неужели вы совсем не дорожите жизнью заложницы?"
    },
    {
      "id": 146,
      "model": "료슈",
      "content": "Ты не посмеешь дать ей умереть, если только не планируешь навлечь на себя гнев красного проводника."
    },
    {
      "id": 147,
      "content": "Как и сказала Рёшу, незваный гость лишь защищался от её ударов, не причиняя вреда Харон."
    },
    {
      "id": 148,
      "content": "Как раз в тот момент, когда остальные Грешники уже собирались присоединиться к атаке..."
    },
    {
      "id": 149,
      "model": "엄지제자",
      "teller": "???",
      "title": "???",
      "content": "Я намеревался сразиться с вами по одному, как того требуют приличия честного поединка, но..."
    },
    {
      "id": 150,
      "model": "엄지제자",
      "teller": "???",
      "title": "???",
      "content": "...к сожалению, раз уж я не могу позволить вам забрать её до прибытия моей госпожи..."
    },
    {
      "id": 151,
      "content": "Незваный гость сделал жест рукой, и странные, причудливые существа с глухим стуком спрыгнули через дыру в потолке."
    },
    {
      "id": 152,
      "model": "엄지제자",
      "teller": "???",
      "title": "???",
      "content": "...мне придётся прибегнуть к использованию некоторого... заимствованного оружия."
    },
    {
      "id": 153,
      "model": "싱클레어",
      "content": "Это Искажения или... какие-то монстры?"
    },
    {
      "id": 154,
      "model": "단테",
      "content": "<Нет...>"
    },
    {
      "id": 155,
      "model": "단테",
      "content": "<Я думаю, это... люди...>"
    },
    {
      "id": 156,
      "model": "히스클리프",
      "content": "Его «госпожа»... Вергилий вроде как способен разобраться с кем бы то ни было, так?"
    },
    {
      "id": 157,
      "model": "돈키호테",
      "content": "Достославнейший Цветной Корректировщик, должно быть, удерживается от использования своей полной мощи из-за захвата юной Харон..."
    },
    {
      "id": 158,
      "model": "히스클리프",
      "content": "Тогда спасаем Харон и валим в штаб или куда там ещё — это позволит проводнику разгуляться по полной."
    },
    {
      "id": 159,
      "model": "이스마엘",
      "content": "Да, похоже, это наш лучший шанс на данный момент."
    },
    {
      "id": 160,
      "model": "단테",
      "content": "<...И всё же, давайте будем осторожны и поставим безопасность Харон превыше всего остального.>"
    }
  ]
}